pygmsh/__about__.py
pygmsh/__init__.py
pygmsh/_cli.py
pygmsh/_optimize.py
pygmsh/helpers.py
pygmsh/common/__init__.py
pygmsh/common/bezier.py
pygmsh/common/bspline.py
pygmsh/common/circle_arc.py
pygmsh/common/curve_loop.py
pygmsh/common/dummy.py
pygmsh/common/ellipse_arc.py
pygmsh/common/geometry.py
pygmsh/common/line.py
pygmsh/common/line_base.py
pygmsh/common/plane_surface.py
pygmsh/common/point.py
pygmsh/common/polygon.py
pygmsh/common/size_field.py
pygmsh/common/spline.py
pygmsh/common/surface.py
pygmsh/common/surface_loop.py
pygmsh/common/volume.py
pygmsh/geo/__init__.py
pygmsh/geo/dummy.py
pygmsh/geo/geometry.py
pygmsh/occ/__init__.py
pygmsh/occ/ball.py
pygmsh/occ/box.py
pygmsh/occ/cone.py
pygmsh/occ/cylinder.py
pygmsh/occ/disk.py
pygmsh/occ/dummy.py
pygmsh/occ/geometry.py
pygmsh/occ/rectangle.py
pygmsh/occ/torus.py
pygmsh/occ/wedge.py
pygmsh-7.1.16.dist-info/entry_points.txt
pygmsh-7.1.16.dist-info/LICENSE.txt
pygmsh-7.1.16.dist-info/WHEEL
pygmsh-7.1.16.dist-info/METADATA
pygmsh-7.1.16.dist-info/RECORD
