Metadata-Version: 2.1
Name: pygmsh
Version: 7.1.16
Summary: Python frontend for Gmsh
Keywords: mesh,gmsh,mesh generation,mathematics,engineering
Author-email: Nico Schlömer <nico.schloemer@gmail.com>
Requires-Python: >=3.7
Classifier: Development Status :: 5 - Production/Stable
Classifier: Intended Audience :: Science/Research
Classifier: License :: OSI Approved :: GNU General Public License v3 or later (GPLv3+)
Classifier: Operating System :: OS Independent
Classifier: Programming Language :: Python
Classifier: Programming Language :: Python :: 3
Classifier: Programming Language :: Python :: 3.7
Classifier: Programming Language :: Python :: 3.8
Classifier: Programming Language :: Python :: 3.9
Classifier: Programming Language :: Python :: 3.10
Classifier: Topic :: Scientific/Engineering
Classifier: Topic :: Scientific/Engineering :: Mathematics
Classifier: Topic :: Utilities
Requires-Dist: gmsh
Requires-Dist: meshio >= 4.3.2, <6
Requires-Dist: numpy >= 1.20.0
Project-URL: Code, https://github.com/nschloe/pygmsh
Project-URL: Documentation, https://pygmsh.readthedocs.io/en/latest
Project-URL: Funding, https://github.com/sponsors/nschloe
Project-URL: Issues, https://github.com/nschloe/pygmsh/issues
